{"_type":"export","__export_format":4,"__export_date":"2023-11-02T00:22:46.002Z","__export_source":"insomnia.desktop.app:v8.3.0","resources":[{"_id":"req_6fa8bb1f37ce4a5f947e58a8a8fcc547","parentId":"fld_b62b3aae08e14d6686b9ae42af61597d","modified":1698884083833,"created":1698883811920,"url":"http://localhost:8080/users","name":"Listar Usuários","description":"","method":"GET","body":{},"parameters":[],"headers":[{"name":"User-Agent","value":"insomnia/8.3.0"}],"authentication":{},"metaSortKey":-1698883811920,"isPrivate":false,"settingStoreCookies":true,"settingSendCookies":true,"settingDisableRenderRequestBody":false,"settingEncodeUrl":true,"settingRebuildPath":true,"settingFollowRedirects":"global","_type":"request"},{"_id":"fld_b62b3aae08e14d6686b9ae42af61597d","parentId":"wrk_8302127009f041c79f9b3d107c00481b","modified":1698884236185,"created":1698883805464,"name":"Users","description":"","environment":{},"environmentPropertyOrder":null,"metaSortKey":-1698884232585,"_type":"request_group"},{"_id":"wrk_8302127009f041c79f9b3d107c00481b","parentId":null,"modified":1698883794638,"created":1698883794638,"name":"React Grupo 6","description":"","scope":"collection","_type":"workspace"},{"_id":"req_2117ab49903943a5b13a72f3bb92a66d","parentId":"fld_b62b3aae08e14d6686b9ae42af61597d","modified":1698884408534,"created":1698883886258,"url":"http://localhost:8080/users","name":"Login","description":"","method":"GET","body":{},"parameters":[{"id":"pair_85465a66efe844bfae2bf435c86d792e","name":"email","value":"","description":""},{"id":"pair_1b097fb441d640e6808ae7b7dddb294d","name":"senha","value":"","description":""}],"headers":[{"name":"User-Agent","value":"insomnia/8.3.0"}],"authentication":{},"metaSortKey":-1698883811820,"isPrivate":false,"settingStoreCookies":true,"settingSendCookies":true,"settingDisableRenderRequestBody":false,"settingEncodeUrl":true,"settingRebuildPath":true,"settingFollowRedirects":"global","_type":"request"},{"_id":"req_485bd87320254b688203cf80bec7539f","parentId":"fld_b62b3aae08e14d6686b9ae42af61597d","modified":1698883942568,"created":1698883919831,"url":"http://localhost:8080/users","name":"Cadastrar","description":"","method":"POST","body":{},"parameters":[],"headers":[{"name":"User-Agent","value":"insomnia/8.3.0"}],"authentication":{},"metaSortKey":-1698883811720,"isPrivate":false,"settingStoreCookies":true,"settingSendCookies":true,"settingDisableRenderRequestBody":false,"settingEncodeUrl":true,"settingRebuildPath":true,"settingFollowRedirects":"global","_type":"request"},{"_id":"req_6acec1ec19db45a48e43072f85be90c9","parentId":"fld_a4fb2a808c1640a29f8dd4eaae1931f5","modified":1698884164202,"created":1698884122861,"url":"http://localhost:8080/users","name":"Listar Produtos","description":"","method":"GET","body":{},"parameters":[],"headers":[{"name":"User-Agent","value":"insomnia/8.3.0"}],"authentication":{},"metaSortKey":-1698884129366,"isPrivate":false,"settingStoreCookies":true,"settingSendCookies":true,"settingDisableRenderRequestBody":false,"settingEncodeUrl":true,"settingRebuildPath":true,"settingFollowRedirects":"global","_type":"request"},{"_id":"fld_a4fb2a808c1640a29f8dd4eaae1931f5","parentId":"wrk_8302127009f041c79f9b3d107c00481b","modified":1698884234304,"created":1698884097868,"name":"Produtos","description":"","environment":{},"environmentPropertyOrder":null,"metaSortKey":-1698884232485,"_type":"request_group"},{"_id":"req_539bc53b484e4db99027518897d872d9","parentId":"fld_a4fb2a808c1640a29f8dd4eaae1931f5","modified":1698884522747,"created":1698884206298,"url":"http://localhost:8080/users","name":"Produto/Categoria","description":"","method":"GET","body":{},"parameters":[{"id":"pair_46051cf373c544538c940205ade8c7b0","name":"categoria","value":"","description":""}],"headers":[{"name":"User-Agent","value":"insomnia/8.3.0"}],"authentication":{},"metaSortKey":-1698883970643,"isPrivate":false,"settingStoreCookies":true,"settingSendCookies":true,"settingDisableRenderRequestBody":false,"settingEncodeUrl":true,"settingRebuildPath":true,"settingFollowRedirects":"global","_type":"request"},{"_id":"req_3f1d60f252c542c4ae17ea5839703e05","parentId":"fld_da15f776aea744469e14a3ce6e13f37d","modified":1698884449344,"created":1698884239741,"url":"http://localhost:8080/pedidos","name":"Pedido/User","description":"","method":"GET","body":{},"parameters":[{"id":"pair_ba6f3b2f366f49328b5e7c3ec8e2aa89","name":"id","value":"","description":""}],"headers":[{"name":"User-Agent","value":"insomnia/8.3.0"}],"authentication":{},"metaSortKey":-1698884239741,"isPrivate":false,"settingStoreCookies":true,"settingSendCookies":true,"settingDisableRenderRequestBody":false,"settingEncodeUrl":true,"settingRebuildPath":true,"settingFollowRedirects":"global","_type":"request"},{"_id":"fld_da15f776aea744469e14a3ce6e13f37d","parentId":"wrk_8302127009f041c79f9b3d107c00481b","modified":1698884232385,"created":1698884232385,"name":"Pedido","description":"","environment":{},"environmentPropertyOrder":null,"metaSortKey":-1698884232385,"_type":"request_group"},{"_id":"env_d3206dc4ff7858a3c0cbcb7ae4ecd0c2653f093a","parentId":"wrk_8302127009f041c79f9b3d107c00481b","modified":1698883794640,"created":1698883794640,"name":"Base Environment","data":{},"dataPropertyOrder":null,"color":null,"isPrivate":false,"metaSortKey":1698883794640,"_type":"environment"},{"_id":"jar_d3206dc4ff7858a3c0cbcb7ae4ecd0c2653f093a","parentId":"wrk_8302127009f041c79f9b3d107c00481b","modified":1698883794642,"created":1698883794642,"name":"Default Jar","cookies":[],"_type":"cookie_jar"}]}